[{"place_id": 231949745, "licence": "Data \u00a9 OpenStreetMap contributors, ODbL 1.0. http://osm.org/copyright", "osm_type": "node", "osm_id": 566174729, "lat": "22.8015194", "lon": "86.2029579", "class": "place", "type": "city", "place_rank": 16, "importance": 0.5168818823324428, "addresstype": "city", "name": "Jamshedpur", "display_name": "Jamshedpur, Golmuri-Cum-Jugsalai, East Singhbhum, Jharkhand, 831001, India", "boundingbox": ["22.6415194", "22.9615194", "86.0429579", "86.3629579"], "geojson": {"type": "Point", "coordinates": [86.2029579, 22.8015194]}}, {"place_id": 229601741, "licence": "Data \u00a9 OpenStreetMap contributors, ODbL 1.0. http://osm.org/copyright", "osm_type": "relation", "osm_id": 16562971, "lat": "21.8753372", "lon": "75.7703163", "class": "boundary", "type": "administrative", "place_rank": 18, "importance": 0.16004000076295108, "addresstype": "city_district", "name": "Jamshedpur", "display_name": "Jamshedpur, Gogaon Tahsil, Khargone, Madhya Pradesh, India", "boundingbox": ["21.8717592", "21.8792508", "75.7625950", "75.7789679"], "geojson": {"type": "Polygon", "coordinates": [[[75.762595, 21.8790088], [75.7630747, 21.8717933], [75.7660306, 21.8717592], [75.7669144, 21.8737647], [75.7675038, 21.8749075], [75.7692792, 21.8750215], [75.773101, 21.87506], [75.7762507, 21.8748406], [75.7786545, 21.8756143], [75.7789679, 21.8772716], [75.7789675, 21.8778586], [75.7761319, 21.8787059], [75.7716374, 21.878667], [75.7664748, 21.8792508], [75.762595, 21.8790088]]]}}, {"place_id": 226474752, "licence": "Data \u00a9 OpenStreetMap contributors, ODbL 1.0. http://osm.org/copyright", "osm_type": "node", "osm_id": 8173283870, "lat": "29.0001834", "lon": "78.8048457", "class": "place", "type": "village", "place_rank": 19, "importance": 0.14670416800183103, "addresstype": "village", "name": "Jamshedpur", "display_name": "Jamshedpur, Thakurdwara, Moradabad, Uttar Pradesh, India", "boundingbox": ["28.9801834", "29.0201834", "78.7848457", "78.8248457"], "geojson": {"type": "Point", "coordinates": [78.8048457, 29.0001834]}}]